MANIFEST.in
README
requirements.txt
setup.cfg
setup.py
Code2pdf/__init__.py
Code2pdf/code2pdf.py
Code2pdf.egg-info/PKG-INFO
Code2pdf.egg-info/SOURCES.txt
Code2pdf.egg-info/dependency_links.txt
Code2pdf.egg-info/entry_points.txt
Code2pdf.egg-info/pbr.json
Code2pdf.egg-info/requires.txt
Code2pdf.egg-info/top_level.txt