Metadata-Version: 1.1
Name: Code2pdf
Version: 0.0.1
Summary: Converts given source code into pdf file with syntax highlighting, line numbers and much more
Home-page: https://github.com/tushar-rishav/code2pdf/
Author: Tushar Gautam
Author-email: tushar.rishav@gmail.com
License: GNU General Public License v3 (GPLv3)
Keywords: reminder,battery,notification,voice alert,python
Platform: UNKNOWN
Classifier: Operating System :: POSIX :: Linux
Classifier: Programming Language :: Python
Classifier: Programming Language :: Python :: 2.7
Classifier: Topic :: System :: Monitoring
